swift/__init__.py
swift/context.py
swift/data_base_provider.py
swift/sql_mapper.py
swift/swift.py
swift_morm-0.1.dist-info/METADATA
swift_morm-0.1.dist-info/RECORD
swift_morm-0.1.dist-info/WHEEL
swift_morm-0.1.dist-info/top_level.txt
