Metadata-Version: 2.1
Name: swift-morm
Version: 0.1
Summary: Swift Morm is a simple object mapper for python
Home-page: https://github.com/PdrLins/swift-morm
Author: Pedro Lins
Author-email: paugustolins@gmail.com
License: UNKNOWN
Platform: UNKNOWN
Classifier: Programming Language :: Python :: 3
Classifier: License :: OSI Approved :: MIT License
Classifier: Operating System :: OS Independent
